{
  "uuid": "BC4t",
  "titre": "",
  "theme": "",
  "niveau": "",
  "metadata": {
    "exo7id": "6424",
    "auteur": "potyag",
    "createdAt": "2011-10-16",
    "hasIndication": "false",
    "hasCorrection": "false",
    "youtube": "",
    "chapitre": "Géométrie projective",
    "sousChapitre": "Géométrie projective",
    "organisation": "exo7",
    "updatedAt": "2025-03-18T18:15:10.385Z"
  },
  "contenu": [
    {
      "id": "b08b4050-6c44-4264-be23-7f59a8ceef33",
      "type": "description",
      "value": {
        "latex": "Cet exercice ne concerne pas directement la géométrie\nprojective mais sera utilisé par la suite.",
        "html": "<p>Cet exercice ne concerne pas directement la géométrie projective mais\nsera utilisé par la suite.</p>\n"
      }
    },
    {
      "id": "7f0d2338-d38d-4023-abcb-897b2b2eac41",
      "type": "question",
      "value": {
        "latex": "Montrer que chaque réflexion par rapport à un hyperplan dans\n$\\R^n$\n  est une application conforme dans  $\\R^n.$ En déduire que chaque\n  isométrie euclidienne et chaque isométrie sphérique sont\n  conformes dans $\\R^n$ et sur $ S^n$ respectivement.",
        "html": "<p>Montrer que chaque réflexion par rapport à un hyperplan dans <span\nclass=\"math inline\">\\(\\R^n\\)</span> est une application conforme dans\n<span class=\"math inline\">\\(\\R^n.\\)</span> En déduire que chaque\nisométrie euclidienne et chaque isométrie sphérique sont conformes dans\n<span class=\"math inline\">\\(\\R^n\\)</span> et sur <span\nclass=\"math inline\">\\(S^n\\)</span> respectivement.</p>\n"
      }
    },
    {
      "id": "3d2c6434-9f21-4ba3-b02c-a4e0abb64b1f",
      "type": "question",
      "value": {
        "latex": "Montrer qu'une application linéaire $A:E\\mapsto E$\n  conserve les angles non-orientés  entre les vecteurs non-nuls ssi $A$\n  est une matrice conforme.",
        "html": "<p>Montrer qu’une application linéaire <span\nclass=\"math inline\">\\(A:E\\mapsto E\\)</span> conserve les angles\nnon-orientés entre les vecteurs non-nuls ssi <span\nclass=\"math inline\">\\(A\\)</span> est une matrice conforme.</p>\n"
      }
    },
    {
      "id": "efe81ab7-8441-42bd-825c-2ed8c36c98a0",
      "type": "question",
      "value": {
        "latex": "Montrer qu'une application $f:D\\mapsto \\R^n$ d'un\n  ouvert $D\\subset \\R^n$ est conforme dans $D$ ssi elle conserve les\n  angles dans $D$.",
        "html": "<p>Montrer qu’une application <span class=\"math inline\">\\(f:D\\mapsto\n\\R^n\\)</span> d’un ouvert <span class=\"math inline\">\\(D\\subset\n\\R^n\\)</span> est conforme dans <span class=\"math inline\">\\(D\\)</span>\nssi elle conserve les angles dans <span\nclass=\"math inline\">\\(D\\)</span>.</p>\n"
      }
    }
  ],
  "preview": "<p>Cet exercice ne concerne pas directement la géométrie projective mais\nsera utilisé par la suite.</p>\n"
}