{
  "uuid": "iz5V",
  "titre": "",
  "theme": "",
  "niveau": "",
  "metadata": {
    "exo7id": "6416",
    "auteur": "potyag",
    "createdAt": "2011-10-16",
    "hasIndication": "false",
    "hasCorrection": "false",
    "youtube": "",
    "chapitre": "Groupe orthogonal et quaternions",
    "sousChapitre": "Groupe orthogonal et quaternions",
    "organisation": "exo7",
    "updatedAt": "2025-03-18T18:15:16.500Z"
  },
  "contenu": [
    {
      "id": "98671cd3-7f8f-42df-a495-8999208972a2",
      "type": "description",
      "value": {
        "latex": "Si $q\\in  S^3$ tel que $q=\\cos\\theta + I\\sin\\theta,\\ I\\in S^2,$ alors montrer\nque $\\rho_q\\in SO(3)$ est la rotation d'angle $2\\theta$ autour de l'axe $OI$.",
        "html": "<p>Si <span class=\"math inline\">\\(q\\in  S^3\\)</span> tel que <span\nclass=\"math inline\">\\(q=\\cos\\theta + I\\sin\\theta,\\ I\\in S^2,\\)</span>\nalors montrer que <span class=\"math inline\">\\(\\rho_q\\in SO(3)\\)</span>\nest la rotation d’angle <span class=\"math inline\">\\(2\\theta\\)</span>\nautour de l’axe <span class=\"math inline\">\\(OI\\)</span>.</p>\n"
      }
    }
  ],
  "preview": "<p>Si <span class=\"math inline\">\\(q\\in  S^3\\)</span> tel que <span\nclass=\"math inline\">\\(q=\\cos\\theta + I\\sin\\theta,\\ I\\in S^2,\\)</span>\nalors montrer ..."
}