{
  "uuid": "K6AQ",
  "titre": "",
  "theme": "",
  "niveau": "",
  "metadata": {
    "exo7id": "2745",
    "auteur": "tumpach",
    "createdAt": "2009-10-25",
    "hasIndication": "false",
    "hasCorrection": "false",
    "youtube": "",
    "chapitre": "Application linéaire",
    "sousChapitre": "Image et noyau, théorème du rang",
    "organisation": "exo7",
    "updatedAt": "2025-03-18T17:57:50.808Z"
  },
  "contenu": [
    {
      "id": "67466d00-32fe-49f3-9b73-9b832e8adf84",
      "type": "description",
      "value": {
        "latex": "Soit la matrice $$B = \\left( \\begin{array}{cccc}1 & 2 & 3 & 1\\\\-1 & 2 & -1 &-3\\\\ -3 & 5 &  2 &-3\\end{array}\\right).$$",
        "html": "<p>Soit la matrice <span class=\"math display\">\\[B = \\left(\n\\begin{array}{cccc}1 &amp; 2 &amp; 3 &amp; 1\\\\-1 &amp; 2 &amp; -1\n&amp;-3\\\\ -3 &amp; 5 &amp;  2 &amp;-3\\end{array}\\right).\\]</span></p>\n"
      }
    },
    {
      "id": "2d9ecbbd-8b17-4b48-b5f9-8e10da4ba94a",
      "type": "question",
      "value": {
        "latex": "D\\'eterminer une base du noyau de $B$.",
        "html": "<p>Déterminer une base du noyau de <span\nclass=\"math inline\">\\(B\\)</span>.</p>\n"
      }
    },
    {
      "id": "eda9dde6-9bfc-4dcb-951c-446aa229e07e",
      "type": "question",
      "value": {
        "latex": "D\\'eterminer une base de l'image de $B$.",
        "html": "<p>Déterminer une base de l’image de <span\nclass=\"math inline\">\\(B\\)</span>.</p>\n"
      }
    }
  ],
  "preview": "<p>Soit la matrice <span class=\"math display\"> ..."
}