{
  "uuid": "xs8z",
  "titre": "",
  "theme": "",
  "niveau": "",
  "metadata": {
    "exo7id": "3124",
    "auteur": "quercia",
    "createdAt": "2010-03-08",
    "hasIndication": "false",
    "hasCorrection": "true",
    "youtube": "",
    "chapitre": "Arithmétique dans Z",
    "sousChapitre": "Pgcd, ppcm, algorithme d'Euclide",
    "organisation": "exo7",
    "updatedAt": "2025-03-18T18:00:30.353Z"
  },
  "contenu": [
    {
      "id": "adfa4858-b0df-4f92-a240-1e8f610e527b",
      "type": "description",
      "value": {
        "latex": "Soient $a,b,c$ trois entiers relatifs. On consid{\\`e}re l'{\\'e}quation : $ax+by=c$,\ndont on recherche les solutions dans $\\Z^2$.",
        "html": "<p>Soient <span class=\"math inline\">\\(a,b,c\\)</span> trois entiers\nrelatifs. On consid<span>è</span>re l’<span>é</span>quation : <span\nclass=\"math inline\">\\(ax+by=c\\)</span>, dont on recherche les solutions\ndans <span class=\"math inline\">\\(\\Z^2\\)</span>.</p>\n"
      }
    },
    {
      "id": "7df10352-fe45-4969-8d55-59e11cdf4f46",
      "type": "question",
      "value": {
        "latex": "Donner une condition n{\\'e}c{\\'e}ssaire et suffisante pour que cette {\\'e}quation admette\n    une solution.",
        "html": "<p>Donner une condition n<span>é</span>c<span>é</span>ssaire et\nsuffisante pour que cette <span>é</span>quation admette une\nsolution.</p>\n"
      }
    },
    {
      "id": "d1051df2-594d-4085-b57d-b74342461baf",
      "type": "question",
      "value": {
        "latex": "Soit $(x_0,y_0)$ une solution du probl{\\`e}me de B{\\'e}zout : $ax_0 + by_0 = d$.\n    D{\\'e}ter\\-miner toutes les solutions de $ax + by = c$ en fonction de $a$, $b$,\n    $c$, $d$, $x_0$ et $y_0$.",
        "html": "<p>Soit <span class=\"math inline\">\\((x_0,y_0)\\)</span> une solution du\nprobl<span>è</span>me de B<span>é</span>zout : <span\nclass=\"math inline\">\\(ax_0 + by_0 = d\\)</span>. D<span>é</span>terminer\ntoutes les solutions de <span class=\"math inline\">\\(ax + by = c\\)</span>\nen fonction de <span class=\"math inline\">\\(a\\)</span>, <span\nclass=\"math inline\">\\(b\\)</span>, <span\nclass=\"math inline\">\\(c\\)</span>, <span\nclass=\"math inline\">\\(d\\)</span>, <span\nclass=\"math inline\">\\(x_0\\)</span> et <span\nclass=\"math inline\">\\(y_0\\)</span>.</p>\n"
      }
    },
    {
      "id": "ec77350b-1ad1-4df4-9db8-5ad0633c954d",
      "type": "question",
      "value": {
        "latex": "R{\\'e}soudre dans $\\Z^2$ : $2520x - 3960y = 6480$.",
        "html": "<p>R<span>é</span>soudre dans <span class=\"math inline\">\\(\\Z^2\\)</span>\n: <span class=\"math inline\">\\(2520x - 3960y = 6480\\)</span>.</p>\n"
      }
    },
    {
      "id": "94b338af-f034-43c6-a61f-9bd1753b4299",
      "type": "reponse",
      "value": {
        "latex": "$x=1+11k,\\quad y=-1+7k$.",
        "html": "<p><span class=\"math inline\">\\(x=1+11k,\\quad y=-1+7k\\)</span>.</p>\n"
      }
    }
  ],
  "preview": "<p>Soient <span class=\"math inline\">\\(a,b,c\\)</span> trois entiers\nrelatifs. On consid<span>è</span>re l’<span>é</span>quation : <span\nclass=\"math inl ..."
}