{
  "uuid": "Hgaf",
  "titre": "",
  "theme": "",
  "niveau": "",
  "metadata": {
    "exo7id": "6163",
    "auteur": "queffelec",
    "createdAt": "2011-10-16",
    "hasIndication": "false",
    "hasCorrection": "false",
    "youtube": "",
    "chapitre": "Connexité",
    "sousChapitre": "Connexité",
    "organisation": "exo7",
    "updatedAt": "2025-03-18T18:02:34.643Z"
  },
  "contenu": [
    {
      "id": "a46e3127-1035-4abe-8f3a-138bdeb71730",
      "type": "description",
      "value": {
        "latex": "Soit $f$ une application continue de $[a,b]$ dans $\\Rr$ vérifiant\n$$f({x+y\\over2})\\leq {1\\over2}\\Big(f(x)+f(y)\\Big)\\quad \\forall x,y\\in [a,b].$$",
        "html": "<p>Soit <span class=\"math inline\">\\(f\\)</span> une application continue\nde <span class=\"math inline\">\\([a,b]\\)</span> dans <span\nclass=\"math inline\">\\(\\Rr\\)</span> vérifiant <span\nclass=\"math display\">\\[f({x+y\\over2})\\leq\n{1\\over2}\\Big(f(x)+f(y)\\Big)\\quad \\forall x,y\\in [a,b].\\]</span></p>\n"
      }
    },
    {
      "id": "2058a0b1-291e-4b2b-8537-fa8b3285aa3c",
      "type": "question",
      "value": {
        "latex": "On suppose $f(a)=f(b)=0$. On considère $E=\\{x\\in ]a,b[\\ /\\\nf(x)=\\displaystyle\\sup_{t\\in[a,b]} f(t)\\}$. Montrer que $E$ est ouvert et\nfermé dans\n$]a,b[$. En déduire que $f$ est $<0$ ou identiquement nulle sur $]a,b[$.",
        "html": "<p>On suppose <span class=\"math inline\">\\(f(a)=f(b)=0\\)</span>. On\nconsidère <span class=\"math inline\">\\(E=\\{x\\in ]a,b[\\ /\\\nf(x)=\\displaystyle\\sup_{t\\in[a,b]} f(t)\\}\\)</span>. Montrer que <span\nclass=\"math inline\">\\(E\\)</span> est ouvert et fermé dans <span\nclass=\"math inline\">\\(]a,b[\\)</span>. En déduire que <span\nclass=\"math inline\">\\(f\\)</span> est <span\nclass=\"math inline\">\\(&lt;0\\)</span> ou identiquement nulle sur <span\nclass=\"math inline\">\\(]a,b[\\)</span>.</p>\n"
      }
    },
    {
      "id": "30b8f3b1-360f-4304-a727-43b1ce16df02",
      "type": "question",
      "value": {
        "latex": "Montrer dans tous les cas que $f$ est convexe ie $f$ vérifie\n$f((1-t)x+ty)\\leq (1-t)f(x)+tf(y)$ pour tous $x,y\\in [a,b]$ et $t\\in[0,1]$ (On se\nramènera au cas a) en considérant\n $f$ privée de sa corde sur $[a,b]$).",
        "html": "<p>Montrer dans tous les cas que <span class=\"math inline\">\\(f\\)</span>\nest convexe ie <span class=\"math inline\">\\(f\\)</span> vérifie <span\nclass=\"math inline\">\\(f((1-t)x+ty)\\leq (1-t)f(x)+tf(y)\\)</span> pour\ntous <span class=\"math inline\">\\(x,y\\in [a,b]\\)</span> et <span\nclass=\"math inline\">\\(t\\in[0,1]\\)</span> (On se ramènera au cas a) en\nconsidérant <span class=\"math inline\">\\(f\\)</span> privée de sa corde\nsur <span class=\"math inline\">\\([a,b]\\)</span>).</p>\n"
      }
    }
  ],
  "preview": "<p>Soit <span class=\"math inline\">\\(f\\)</span> une application continue\nde <span class=\"math inline\">\\([a,b]\\)</span> dans <span\nclass=\"math inline\">\\ ..."
}