{
  "uuid": "TptL",
  "titre": "",
  "theme": "",
  "niveau": "",
  "metadata": {
    "exo7id": "6067",
    "auteur": "queffelec",
    "createdAt": "2011-10-16",
    "hasIndication": "false",
    "hasCorrection": "false",
    "youtube": "",
    "chapitre": "Continuité, uniforme continuité",
    "sousChapitre": "Continuité, uniforme continuité",
    "organisation": "exo7",
    "updatedAt": "2025-03-18T18:02:44.187Z"
  },
  "contenu": [
    {
      "id": "86abe1cf-4996-4823-aaa7-0b448ad08c62",
      "type": "description",
      "value": {
        "latex": "Soit $f$ une application de $\\R$ dans $\\R$, telle que $f(x+y)=f(x)+f(y)$\net $f(xy)=f(x)f(y)$ pour tous $x,y\\in \\R$. On va montrer que $f$ est soit\nnulle, soit la fonction identité.",
        "html": "<p>Soit <span class=\"math inline\">\\(f\\)</span> une application de <span\nclass=\"math inline\">\\(\\R\\)</span> dans <span\nclass=\"math inline\">\\(\\R\\)</span>, telle que <span\nclass=\"math inline\">\\(f(x+y)=f(x)+f(y)\\)</span> et <span\nclass=\"math inline\">\\(f(xy)=f(x)f(y)\\)</span> pour tous <span\nclass=\"math inline\">\\(x,y\\in \\R\\)</span>. On va montrer que <span\nclass=\"math inline\">\\(f\\)</span> est soit nulle, soit la fonction\nidentité.</p>\n"
      }
    },
    {
      "id": "e97bb02a-96ae-4ef5-ae3d-b482be5fa3af",
      "type": "question",
      "value": {
        "latex": "Remarquer que $f(x)\\geq0$ si\n$x\\geq0$ et ainsi, que $f$ est croissante.",
        "html": "<p>Remarquer que <span class=\"math inline\">\\(f(x)\\geq0\\)</span> si <span\nclass=\"math inline\">\\(x\\geq0\\)</span> et ainsi, que <span\nclass=\"math inline\">\\(f\\)</span> est croissante.</p>\n"
      }
    },
    {
      "id": "84438b3b-0532-495f-9fed-a191d2bf16d4",
      "type": "question",
      "value": {
        "latex": "Montrer que pour tout $x$ réel on peut construire une suite $(r_k)$ et une\nsuite $(s_k)$ de rationnels telles que $r_k\\uparrow x$ et $s_k\\downarrow x$.\nEn déduire le résultat.",
        "html": "<p>Montrer que pour tout <span class=\"math inline\">\\(x\\)</span> réel on\npeut construire une suite <span class=\"math inline\">\\((r_k)\\)</span> et\nune suite <span class=\"math inline\">\\((s_k)\\)</span> de rationnels\ntelles que <span class=\"math inline\">\\(r_k\\uparrow x\\)</span> et <span\nclass=\"math inline\">\\(s_k\\downarrow x\\)</span>. En déduire le\nrésultat.</p>\n"
      }
    }
  ],
  "preview": "<p>Soit <span class=\"math inline\">\\(f\\)</span> une application de <span\nclass=\"math inline\">\\(\\R\\)</span> dans <span\nclass=\"math inline\">\\(\\R\\)</span> ..."
}