{
  "uuid": "427f5d23-29a2-44a1-9ae2-e372a886da99",
  "titre": "",
  "theme": "",
  "niveau": "",
  "metadata": {
    "exo7id": "7904",
    "auteur": "mourougane",
    "createdAt": "2021-08-11",
    "hasIndication": false,
    "hasCorrection": false,
    "youtube": "",
    "chapitre": "",
    "sousChapitre": "",
    "organisation": "exo7",
    "updatedAt": "2025-03-18T18:14:41.039Z"
  },
  "contenu": [
    {
      "id": "530b1d85-d856-41f9-9ba2-7080a2faba48",
      "type": "description",
      "value": {
        "latex": "",
        "html": "\n"
      }
    },
    {
      "id": "ca6c3a07-0553-4b3a-8711-213a3e9d1d39",
      "type": "question",
      "value": {
        "latex": "Construire à la règle et au compas la tangente à un cercle $\\mathcal{C}$ passant par un point $A$ hors du disque délimité par $\\mathcal{C}$.",
        "html": "<p>Construire à la règle et au compas la tangente à un cercle <span\nclass=\"math inline\">\\(\\mathcal{C}\\)</span> passant par un point <span\nclass=\"math inline\">\\(A\\)</span> hors du disque délimité par <span\nclass=\"math inline\">\\(\\mathcal{C}\\)</span>.</p>\n"
      }
    },
    {
      "id": "a81584e7-5972-41bb-96ae-66a552e1393e",
      "type": "question",
      "value": {
        "latex": "Soit maintenant $\\mathcal{C}$ et $\\mathcal{C}'$ deux cercles non concentriques. Construire les centres $\\Omega$ et $O$ des homothéties qui envoient $\\mathcal{C}$ sur $\\mathcal{C}'$.",
        "html": "<p>Soit maintenant <span class=\"math inline\">\\(\\mathcal{C}\\)</span> et\n<span class=\"math inline\">\\(\\mathcal{C}&#39;\\)</span> deux cercles non\nconcentriques. Construire les centres <span\nclass=\"math inline\">\\(\\Omega\\)</span> et <span\nclass=\"math inline\">\\(O\\)</span> des homothéties qui envoient <span\nclass=\"math inline\">\\(\\mathcal{C}\\)</span> sur <span\nclass=\"math inline\">\\(\\mathcal{C}&#39;\\)</span>.</p>\n"
      }
    },
    {
      "id": "e28e3abf-7339-485f-b182-7536f71e6dd9",
      "type": "question",
      "value": {
        "latex": "Construire deux tangentes communes à $\\mathcal{C}$ et à $\\mathcal{C}'$.",
        "html": "<p>Construire deux tangentes communes à <span\nclass=\"math inline\">\\(\\mathcal{C}\\)</span> et à <span\nclass=\"math inline\">\\(\\mathcal{C}&#39;\\)</span>.</p>\n"
      }
    }
  ],
  "preview": "<p>Construire à la règle et au compas la tangente à un cercle <span\nclass=\"math inline\">\\(\\mathcal{C}\\)</span> passant par un point <span\nclass=\"math  ..."
}