{
  "resume": "Cet exercice évalue la compréhension et l'application de la notion d'équivalence de fonctions au voisinage d'un point (fini ou infini). Il requiert de vérifier si des affirmations du type $f(x) \\underset{x\\to a}{\\sim} g(x)$ sont vraies, en justifiant par la définition de l'équivalence, c'est-à-dire en vérifiant si $\\lim_{x \\to a} \\frac{f(x)}{g(x)} = 1$. L'exercice couvre des fonctions polynomiales, logarithmiques, exponentielles et rationnelles.",
  "competences": [
    "appliquer la définition d'équivalence de fonctions",
    "calculer des limites de fonctions",
    "simplifier des expressions algébriques",
    "interpréter le comportement asymptotique de fonctions",
    "identifier les termes prépondérants dans une expression"
  ],
  "niveau_difficulte": "intermédiaire",
  "mots_cles": [
    "équivalence",
    "fonctions",
    "limite",
    "asymptote",
    "comportement asymptotique",
    "négligeable",
    "croissance comparée",
    "infini"
  ],
  "concepts_fondamentaux": [
    "définition d'équivalence de fonctions",
    "limites à l'infini",
    "équivalents usuels"
  ],
  "prerequis": [
    "connaissance des fonctions usuelles (polynômes, exponentielles, logarithmes, racines carrées)",
    "maîtrise des opérations algébriques élémentaires",
    "notion de limite d'une fonction en un point et à l'infini"
  ],
  "type_exercice": "Exercice d'application directe",
  "temps_estime": "30-45 minutes"
}