{
  "uuid": "tn74",
  "titre": "",
  "theme": "",
  "niveau": "",
  "metadata": {
    "exo7id": "5020",
    "auteur": "quercia",
    "createdAt": "2010-03-17",
    "hasIndication": "false",
    "hasCorrection": "true",
    "youtube": "",
    "chapitre": "Courbes planes",
    "sousChapitre": "Enveloppes",
    "organisation": "exo7",
    "updatedAt": "2025-03-18T18:14:19.897Z"
  },
  "contenu": [
    {
      "id": "01678a46-b042-416d-a746-58126b6c7643",
      "type": "description",
      "value": {
        "latex": "Tracer la courbe d'équation polaire $\\rho = \\frac{a}{\\cos 3\\theta}$, $a>0$.\nChercher l'enveloppe des cordes vues de $O$ sous un angle droit.",
        "html": "<p>Tracer la courbe d’équation polaire <span class=\"math inline\">\\(\\rho\n= \\frac{a}{\\cos 3\\theta}\\)</span>, <span\nclass=\"math inline\">\\(a&gt;0\\)</span>. Chercher l’enveloppe des cordes\nvues de <span class=\"math inline\">\\(O\\)</span> sous un angle droit.</p>\n"
      }
    },
    {
      "id": "e2498099-1184-48ba-bc42-207974886a94",
      "type": "reponse",
      "value": {
        "latex": "$x = a\\cos 4\\theta$, $y = a\\sin 4\\theta$.",
        "html": "<p><span class=\"math inline\">\\(x = a\\cos 4\\theta\\)</span>, <span\nclass=\"math inline\">\\(y = a\\sin 4\\theta\\)</span>.</p>\n"
      }
    }
  ],
  "preview": "<p>Tracer la courbe d’équation polaire <span class=\"math inline\">\\(\\rho\n= \\frac{a}{\\cos 3\\theta}\\)</span>, <span\nclass=\"math inline\">\\(a&gt;0\\)</span> ..."
}