{
  "uuid": "IrDr",
  "titre": "",
  "theme": "",
  "niveau": "",
  "metadata": {
    "exo7id": "2255",
    "auteur": "barraud",
    "createdAt": "2008-04-24",
    "hasIndication": "false",
    "hasCorrection": "false",
    "youtube": "",
    "chapitre": "Anneau, corps",
    "sousChapitre": "Anneau, corps",
    "organisation": "exo7",
    "updatedAt": "2025-03-18T18:00:50.192Z"
  },
  "contenu": [
    {
      "id": "44c93536-8917-4d6f-a4da-6535b56d4681",
      "type": "description",
      "value": {
        "latex": "Les \\'el\\'ements inversibles d'un anneau $A$\nforment le groupe multiplicatif $(A^{\\times}, \\cdot)$.",
        "html": "<p>Les éléments inversibles d’un anneau <span\nclass=\"math inline\">\\(A\\)</span> forment le groupe multiplicatif <span\nclass=\"math inline\">\\((A^{\\times}, \\cdot)\\)</span>.</p>\n"
      }
    },
    {
      "id": "4a2549d2-195c-4a71-a925-230701409ff7",
      "type": "question",
      "value": {
        "latex": "Trouver $A^{\\times}$ pour les anneaux 1. et 2. \nde l'exercice \\ref{exodessus}.",
        "html": "<p>Trouver <span class=\"math inline\">\\(A^{\\times}\\)</span> pour les\nanneaux 1. et 2. de l’exercice <a href=\"#exodessus\"\ndata-reference-type=\"ref\"\ndata-reference=\"exodessus\">[exodessus]</a>.</p>\n"
      }
    },
    {
      "id": "877a6067-bdd4-4663-b808-f7b0e2b888a3",
      "type": "question",
      "value": {
        "latex": "Trouver le groupe $\\Zz[\\sqrt{-1}]^{\\times}$ en utilisant \nla norme complexe.",
        "html": "<p>Trouver le groupe <span\nclass=\"math inline\">\\(\\Zz[\\sqrt{-1}]^{\\times}\\)</span> en utilisant la\nnorme complexe.</p>\n"
      }
    },
    {
      "id": "a3249bd1-8a1b-4da2-ab8a-b540121eebb5",
      "type": "question",
      "value": {
        "latex": "Montrer que le groupe $\\Zz[\\sqrt{2}]^{\\times}$ est infini.",
        "html": "<p>Montrer que le groupe <span\nclass=\"math inline\">\\(\\Zz[\\sqrt{2}]^{\\times}\\)</span> est infini.</p>\n"
      }
    }
  ],
  "preview": "<p>Les éléments inversibles d’un anneau <span\nclass=\"math inline\">\\(A\\)</span> forment le groupe multiplicatif <span\nclass=\"math inline\"> ..."
}