{
  "uuid": "ASZr",
  "titre": "",
  "theme": "",
  "niveau": "",
  "metadata": {
    "exo7id": "2509",
    "auteur": "queffelec",
    "createdAt": "2009-04-01",
    "hasIndication": "false",
    "hasCorrection": "false",
    "youtube": "",
    "chapitre": "Différentiabilité, calcul de différentielles",
    "sousChapitre": "Différentiabilité, calcul de différentielles",
    "organisation": "exo7",
    "updatedAt": "2025-03-18T18:01:39.668Z"
  },
  "contenu": [
    {
      "id": "c4efe430-01ab-4190-9b3e-29f28a709f9e",
      "type": "description",
      "value": {
        "latex": "Soit $E$ un espace de\nBanach et ${\\cal L}(E)$ l'espace des endomorphismes lin\\'eaires\ncontinus de $E$.",
        "html": "<p>Soit <span class=\"math inline\">\\(E\\)</span> un espace de Banach et\n<span class=\"math inline\">\\({\\cal L}(E)\\)</span> l’espace des\nendomorphismes linéaires continus de <span\nclass=\"math inline\">\\(E\\)</span>.</p>\n"
      }
    },
    {
      "id": "10437515-3629-430a-9931-14466889044c",
      "type": "question",
      "value": {
        "latex": "Soit $A\\in{\\cal L}(E)$; montrer que l'application\n$\\varphi:t\\in{\\Rr}\\to e^{tA}$ est d\\'erivable et calculer sa\nd\\'eriv\\'ee.",
        "html": "<p>Soit <span class=\"math inline\">\\(A\\in{\\cal L}(E)\\)</span>; montrer\nque l’application <span class=\"math inline\">\\(\\varphi:t\\in{\\Rr}\\to\ne^{tA}\\)</span> est dérivable et calculer sa dérivée.</p>\n"
      }
    },
    {
      "id": "4a01e9d7-af7c-49f5-b818-c5306ed470f9",
      "type": "question",
      "value": {
        "latex": "On suppose que la norme de $E$ est associ\\'ee au produit\nscalaire $\\langle \\cdot,\\cdot\\rangle$. Soit $x\\in E$. Montrer que\nl'application $\\Phi:t\\to \\langle e^{tA}x,e^{tA}x\\rangle$ est\nd\\'erivable et calculer sa d\\'eriv\\'ee.",
        "html": "<p>On suppose que la norme de <span class=\"math inline\">\\(E\\)</span> est\nassociée au produit scalaire <span class=\"math inline\">\\(\\langle\n\\cdot,\\cdot\\rangle\\)</span>. Soit <span class=\"math inline\">\\(x\\in\nE\\)</span>. Montrer que l’application <span\nclass=\"math inline\">\\(\\Phi:t\\to \\langle e^{tA}x,e^{tA}x\\rangle\\)</span>\nest dérivable et calculer sa dérivée.</p>\n"
      }
    },
    {
      "id": "2428632a-94bc-418c-9515-f03c6bb07d6f",
      "type": "question",
      "value": {
        "latex": "On suppose que $A$ est antisym\\'etrique. Montrer que pour\ntout $t$, $e^{tA}$ est unitaire.",
        "html": "<p>On suppose que <span class=\"math inline\">\\(A\\)</span> est\nantisymétrique. Montrer que pour tout <span\nclass=\"math inline\">\\(t\\)</span>, <span\nclass=\"math inline\">\\(e^{tA}\\)</span> est unitaire.</p>\n"
      }
    }
  ],
  "preview": "<p>Soit <span class=\"math inline\">\\(E\\)</span> un espace de Banach et\n<span class=\"math inline\">\\({\\cal L}(E)\\)</span> l’espace des\nendomorphismes lin ..."
}