{
  "uuid": "ERfb",
  "titre": "",
  "theme": "",
  "niveau": "",
  "metadata": {
    "exo7id": "6796",
    "auteur": "gijs",
    "createdAt": "2011-10-16",
    "hasIndication": "false",
    "hasCorrection": "false",
    "youtube": "",
    "chapitre": "Différentiabilité, calcul de différentielles",
    "sousChapitre": "Différentiabilité, calcul de différentielles",
    "organisation": "exo7",
    "updatedAt": "2025-03-18T18:01:40.979Z"
  },
  "contenu": [
    {
      "id": "673f3194-6b74-4ebd-82c4-8b10add6b606",
      "type": "description",
      "value": {
        "latex": "",
        "html": "\n"
      }
    },
    {
      "id": "2aa29e85-20ca-4e2f-9b34-8e424586458d",
      "type": "question",
      "value": {
        "latex": "Enoncer le théorème des accroissements finis pour\nune fonction $f:\\Rr^n \\to \\Rr^p$.",
        "html": "<p>Enoncer le théorème des accroissements finis pour une fonction <span\nclass=\"math inline\">\\(f:\\Rr^n \\to \\Rr^p\\)</span>.</p>\n"
      }
    },
    {
      "id": "706b30ee-91a4-4364-af3f-ad4d6d27b018",
      "type": "question",
      "value": {
        "latex": "Soit $B_\\epsilon(x_o)$ la boule de rayon\n$\\epsilon$ dans $\\Rr^n$, et soit $f:\n\\overline{B_\\epsilon(x_o)} \\to \\Rr$ une fonction de\nclasse $C^1$. Montrer que $f$ est Lipschitzienne et donner\nune expression de son rapport.",
        "html": "<p>Soit <span class=\"math inline\">\\(B_\\epsilon(x_o)\\)</span> la boule de\nrayon <span class=\"math inline\">\\(\\epsilon\\)</span> dans <span\nclass=\"math inline\">\\(\\Rr^n\\)</span>, et soit <span\nclass=\"math inline\">\\(f:\n\\overline{B_\\epsilon(x_o)} \\to \\Rr\\)</span> une fonction de classe <span\nclass=\"math inline\">\\(C^1\\)</span>. Montrer que <span\nclass=\"math inline\">\\(f\\)</span> est Lipschitzienne et donner une\nexpression de son rapport.</p>\n"
      }
    }
  ],
  "preview": "<p>Enoncer le théorème des accroissements finis pour une fonction <span\nclass=\"math inline\">\\(f:\\Rr^n \\to \\Rr^p\\)</span>.</p>\n"
}