{
  "uuid": "4pUk",
  "titre": "",
  "theme": "",
  "niveau": "",
  "metadata": {
    "exo7id": "6631",
    "auteur": "queffelec",
    "createdAt": "2011-10-16",
    "hasIndication": "false",
    "hasCorrection": "false",
    "youtube": "",
    "chapitre": "Fonction holomorphe",
    "sousChapitre": "Fonction holomorphe",
    "organisation": "exo7",
    "updatedAt": "2025-03-18T18:03:14.830Z"
  },
  "contenu": [
    {
      "id": "42e04170-8e15-48c4-baae-45847f3a229b",
      "type": "description",
      "value": {
        "latex": "Déterminer le rayon de convergence des séries\n$\\sum_{n\\ge 0}a^nz^n$ ($a\\in \\C$) ; $\\sum_{n\\ge 0}e^{\\sqrt n}z^n$ ; \n$\\sum_{n\\ge 0}z^n/n!$ ; $\\sum_{n\\ge 0}z^{2n}$ ; \n$\\sum_{n\\ge 0}z^{n!}$.\n\nComparer le rayon de convergence des séries $\\sum_{n\\ge 0}c_nz^n$ et\n$\\sum_{n\\ge 0}c_nz^{2n}$.\n\nSi le rayon de convergence de $\\sum_{n\\ge 0}c_nz^n$ est strictement positif\net fini, quel est celui de $\\sum_{n\\ge 0}c_nz^{n^2}$ ?",
        "html": "<p>Déterminer le rayon de convergence des séries <span\nclass=\"math inline\">\\(\\sum_{n\\ge 0}a^nz^n\\)</span> (<span\nclass=\"math inline\">\\(a\\in \\C\\)</span>) ; <span\nclass=\"math inline\">\\(\\sum_{n\\ge 0}e^{\\sqrt n}z^n\\)</span> ; <span\nclass=\"math inline\">\\(\\sum_{n\\ge 0}z^n/n!\\)</span> ; <span\nclass=\"math inline\">\\(\\sum_{n\\ge 0}z^{2n}\\)</span> ; <span\nclass=\"math inline\">\\(\\sum_{n\\ge 0}z^{n!}\\)</span>.</p>\n<p>Comparer le rayon de convergence des séries <span\nclass=\"math inline\">\\(\\sum_{n\\ge 0}c_nz^n\\)</span> et <span\nclass=\"math inline\">\\(\\sum_{n\\ge 0}c_nz^{2n}\\)</span>.</p>\n<p>Si le rayon de convergence de <span class=\"math inline\">\\(\\sum_{n\\ge\n0}c_nz^n\\)</span> est strictement positif et fini, quel est celui de\n<span class=\"math inline\">\\(\\sum_{n\\ge 0}c_nz^{n^2}\\)</span> ?</p>\n"
      }
    }
  ],
  "preview": "<p>Déterminer le rayon de convergence des séries <span\nclass=\"math inline\">\\(\\sum_{n\\ge 0}a^nz^n\\)</span> (<span\nclass=\"math inline\">\\(a\\in \\C\\)</span ..."
}