{
  "uuid": "swlF",
  "titre": "",
  "theme": "",
  "niveau": "",
  "metadata": {
    "exo7id": "6700",
    "auteur": "queffelec",
    "createdAt": "2011-10-16",
    "hasIndication": "false",
    "hasCorrection": "false",
    "youtube": "",
    "chapitre": "Formule de Cauchy",
    "sousChapitre": "Formule de Cauchy",
    "organisation": "exo7",
    "updatedAt": "2025-03-18T18:04:17.670Z"
  },
  "contenu": [
    {
      "id": "041db21c-3be6-4f5b-8fec-ee93ca42c990",
      "type": "description",
      "value": {
        "latex": "Montrer qu'une fonction entière admettant 1 et $i$ comme périodes\nest constante.",
        "html": "<p>Montrer qu’une fonction entière admettant 1 et <span\nclass=\"math inline\">\\(i\\)</span> comme périodes est constante.</p>\n"
      }
    }
  ],
  "preview": "<p>Montrer qu’une fonction entière admettant 1 et <span\nclass=\"math inline\">\\(i\\)</span> comme périodes est constante.</p>\n"
}