{
  "uuid": "EG9l",
  "titre": "",
  "theme": "",
  "niveau": "",
  "metadata": {
    "exo7id": "3884",
    "auteur": "quercia",
    "createdAt": "2010-03-11",
    "hasIndication": "false",
    "hasCorrection": "true",
    "youtube": "",
    "chapitre": "Continuité, limite et étude de fonctions réelles",
    "sousChapitre": "Etude de fonctions",
    "organisation": "exo7",
    "updatedAt": "2025-03-18T18:05:16.009Z"
  },
  "contenu": [
    {
      "id": "81a26fa7-cbad-4f1d-b604-50aa09aaaa5e",
      "type": "description",
      "value": {
        "latex": "Soit $f : \\R \\to \\R$ continue telle que~:\n$\\forall\\ x\\in\\R,\\ \\exists\\ \\delta>0,\\text{ tq }\\forall\\ y\\in[x,x+\\delta],\\ f(y)\\ge f(x)$.\nMontrer que $f$ est croissante.",
        "html": "<p>Soit <span class=\"math inline\">\\(f : \\R \\to \\R\\)</span> continue\ntelle que : <span class=\"math inline\">\\(\\forall\\ x\\in\\R,\\ \\exists\\\n\\delta&gt;0,\\text{ tq }\\forall\\ y\\in[x,x+\\delta],\\ f(y)\\ge\nf(x)\\)</span>. Montrer que <span class=\"math inline\">\\(f\\)</span> est\ncroissante.</p>\n"
      }
    },
    {
      "id": "61a16648-dbae-4bc6-95a1-ddc97a383f20",
      "type": "reponse",
      "value": {
        "latex": "Supposons qu'il existe $a,b\\in\\R$ avec $a<b$ et $f(b)<f(a)$.\nOn note $E=\\{x\\in{[a,b]}\\text{ tq }f(x) < f(a)\\}$ et $c=\\inf(E)$.\nOn a $c\\in E$ et $c>a$ par hypothèse et donc $f(c)=\\lim_{x\\to c^-}f(x)\\ge f(a)$, absurde.",
        "html": "<p>Supposons qu’il existe <span class=\"math inline\">\\(a,b\\in\\R\\)</span>\navec <span class=\"math inline\">\\(a&lt;b\\)</span> et <span\nclass=\"math inline\">\\(f(b)&lt;f(a)\\)</span>. On note <span\nclass=\"math inline\">\\(E=\\{x\\in{[a,b]}\\text{ tq }f(x) &lt;\nf(a)\\}\\)</span> et <span class=\"math inline\">\\(c=\\inf(E)\\)</span>. On a\n<span class=\"math inline\">\\(c\\in E\\)</span> et <span\nclass=\"math inline\">\\(c&gt;a\\)</span> par hypothèse et donc <span\nclass=\"math inline\">\\(f(c)=\\lim_{x\\to c^-}f(x)\\ge f(a)\\)</span>,\nabsurde.</p>\n"
      }
    }
  ],
  "preview": "<p>Soit <span class=\"math inline\">\\(f : \\R \\to \\R\\)</span> continue\ntelle que : <span class=\"math inline\"> ..."
}