{
  "uuid": "JtYS",
  "titre": "",
  "theme": "",
  "niveau": "",
  "metadata": {
    "exo7id": "876",
    "auteur": "ridde",
    "createdAt": "1999-11-01",
    "hasIndication": "false",
    "hasCorrection": "false",
    "youtube": "",
    "chapitre": "Equation différentielle",
    "sousChapitre": "Résolution d'équation différentielle du deuxième ordre",
    "organisation": "exo7",
    "updatedAt": "2025-03-18T18:10:58.233Z"
  },
  "contenu": [
    {
      "id": "7c5508de-b147-4c75-8467-d92b3b171b33",
      "type": "description",
      "value": {
        "latex": "R\\'esoudre en posant $z (t) = y (e^t)$ ou $y (-e^t)$ suivant le signe de $x$, les\n\\'equations diff\\'erentielles (d'Euler) suivantes :",
        "html": "<p>Résoudre en posant <span class=\"math inline\">\\(z (t) = y\n(e^t)\\)</span> ou <span class=\"math inline\">\\(y (-e^t)\\)</span> suivant\nle signe de <span class=\"math inline\">\\(x\\)</span>, les équations\ndifférentielles (d’Euler) suivantes :</p>\n"
      }
    },
    {
      "id": "963b64f4-dc18-43a0-931a-a767f930a554",
      "type": "question",
      "value": {
        "latex": "$x^2y''-2y = x$.",
        "html": "<p><span class=\"math inline\">\\(x^2y&#39;&#39;-2y = x\\)</span>.</p>\n"
      }
    },
    {
      "id": "acee7fed-d750-4533-9378-c2b7347ce661",
      "type": "question",
      "value": {
        "latex": "$x^2y'' + xy' + y = x \\ln \\left|x\\right|$.",
        "html": "<p><span class=\"math inline\">\\(x^2y&#39;&#39; + xy&#39; + y = x \\ln\n\\left|x\\right|\\)</span>.</p>\n"
      }
    }
  ],
  "preview": "<p>Résoudre en posant <span class=\"math inline\">\\(z (t) = y\n(e^t)\\)</span> ou <span class=\"math inline\">\\(y (-e^t)\\)</span> suivant\nle signe de <span  ..."
}